{
  "Coins": [
    {
      "UserId": 1304197495,
      "Value": 1028,
      "Name": "DevBarp"
    },
    {
      "UserId": 1527189079,
      "Value": 360,
      "Name": "Svaiper228"
    },
    {
      "UserId": 3391947286,
      "Value": 274,
      "Name": "kaptohka229"
    },
    {
      "UserId": 8142759373,
      "Value": 47,
      "Name": "apolonshhaa"
    },
    {
      "UserId": 3980555544,
      "Value": 38,
      "Name": "Maxim_Wot1"
    },
    {
      "UserId": 1959622759,
      "Value": 29,
      "Name": "Bacek090"
    },
    {
      "UserId": 2359978114,
      "Value": 6,
      "Name": "gfjrrsurge"
    }
  ],
  "Donated": [
    {
      "UserId": 1304197495,
      "Value": 175,
      "Name": "DevBarp"
    }
  ],
  "Raised": [
    {
      "UserId": 1959622759,
      "Value": 100,
      "Name": "Bacek090"
    },
    {
      "UserId": 3391947286,
      "Value": 50,
      "Name": "kaptohka229"
    },
    {
      "UserId": 1527189079,
      "Value": 25,
      "Name": "Svaiper228"
    }
  ],
  "Playtime": [
    {
      "UserId": 1304197495,
      "Value": 6786,
      "Name": "DevBarp"
    },
    {
      "UserId": 1527189079,
      "Value": 4385,
      "Name": "Svaiper228"
    },
    {
      "UserId": 3391947286,
      "Value": 3934,
      "Name": "kaptohka229"
    },
    {
      "UserId": 3980555544,
      "Value": 2304,
      "Name": "Maxim_Wot1"
    },
    {
      "UserId": 2359978114,
      "Value": 1307,
      "Name": "gfjrrsurge"
    },
    {
      "UserId": 1959622759,
      "Value": 990,
      "Name": "Bacek090"
    },
    {
      "UserId": 8142759373,
      "Value": 678,
      "Name": "apolonshhaa"
    }
  ]
}